{
  "ok": true,
  "page_kind": "fill_form",
  "field_mapping": {
    "plaka_no": "#plateNo"
  },
  "actions": [
    "devam"
  ],
  "validation": {
    "contexts": {
      "plaka_no": {
        "tag": "input",
        "id": "plateNo",
        "name": null
      }
    },
    "counts": {
      "mapped": 1
    }
  },
  "mapping_source": {
    "plaka_no": "static_synonym"
  },
  "fingerprint": "799316bfbb5681837ebd129c7825910fe81edbecfe61034da4196ec9bac88b70",
  "debug_dumps": {
    "used": "static",
    "used_hints": {},
    "used_sections": false
  },
  "used": "static"
}